sequence_edits/__init__.py
sequence_edits/main.py
sequence_edits/types.py
sequence_edits-0.1.9.dist-info/METADATA
sequence_edits-0.1.9.dist-info/WHEEL
sequence_edits-0.1.9.dist-info/top_level.txt
sequence_edits-0.1.9.dist-info/RECORD
