Metadata-Version: 2.1
Name: sequence-edits
Version: 0.1.9
Summary: Compressed representation of sequence edits
Author-email: Marcel Claramunt <marcel@moveread.com>
Project-URL: repo, https://github.com/moveread/sequence-edits.git
Requires-Python: >=3.10
